movoid_tools/__init__.py
movoid_tools/mv_import.py
movoid_tools/movoid_config/__init__.py
movoid_tools/movoid_config/mv_config.py
movoid_tools/movoid_copy/__init__.py
movoid_tools/movoid_copy/mv_file_copy.py
movoid_tools/movoid_copy/test_excel.py
movoid_tools/movoid_file/__init__.py
movoid_tools/movoid_file/mv_csv.py
movoid_tools/movoid_file/mv_excel.py
movoid_tools/movoid_log/__init__.py
movoid_tools/movoid_log/mv_log.py
movoid_tools/movoid_test/__init__.py
movoid_tools/movoid_time/__init__.py
movoid_tools/movoid_time/mv_time.py
movoid_tools-1.1.8.1.dist-info/LICENSE
movoid_tools-1.1.8.1.dist-info/METADATA
movoid_tools-1.1.8.1.dist-info/WHEEL
movoid_tools-1.1.8.1.dist-info/top_level.txt
movoid_tools-1.1.8.1.dist-info/RECORD
