Metadata-Version: 2.1
Name: movoid-tools
Version: 1.1.8.1
Summary: mo void create a lot of tools to use in many situations.
Author: SunYiFan-MoVoid
Author-email: bobrobotsun@163.com
License: MIT
License-File: LICENSE
